[
  {
    "clustername": "AD",
    "names": ["Andorra","George"]
  },
  {
    "clustername": "AD",
    "names": "Andorra"
  },
  {
    "clustername": "AD",
    "names": ["Andorra","George"]
  },{
  "clustername": "AD",
  "names": ["Andorra","George"]
},{
  "clustername": "AD",
  "names": ["Andorra","George"]
},{
  "clustername": "AD",
  "names": ["Andorra","George"]
},{
  "clustername": "AD",
  "names": ["Andorra","George"]
},{
  "clustername": "AD",
  "names": ["Andorra","George"]
}
]